alphaavatar/plugins/memory/__init__.py
alphaavatar/plugins/memory/log.py
alphaavatar/plugins/memory/memory_langchain.py
alphaavatar/plugins/memory/memory_op.py
alphaavatar/plugins/memory/memory_prompts.py
alphaavatar/plugins/memory/version.py
alphaavatar/plugins/memory/runner/__init__.py
alphaavatar/plugins/memory/runner/qdrant_runner.py
alpha_avatar_plugins_memory-0.4.0.dist-info/METADATA
alpha_avatar_plugins_memory-0.4.0.dist-info/WHEEL
alpha_avatar_plugins_memory-0.4.0.dist-info/RECORD
